oxli-0.3.0.dist-info/METADATA
oxli-0.3.0.dist-info/WHEEL
oxli-0.3.0.dist-info/licenses/LICENSE
oxli/__init__.py
oxli/oxli.cpython-312-i386-linux-gnu.so
oxli-0.3.0.dist-info/RECORD
