Metadata-Version: 2.3
Name: oxli
Version: 0.3.0
Classifier: Programming Language :: Rust
Classifier: Programming Language :: Python :: Implementation :: CPython
Classifier: Programming Language :: Python :: Implementation :: PyPy
Requires-Dist: pytest >=7.0 ; extra == 'test'
Requires-Dist: toml >=0.10 ; extra == 'test'
Requires-Dist: scipy ; extra == 'test'
Provides-Extra: test
License-File: LICENSE
Summary: oxli is a Rust library + Python interface for counting k-mers in genomic sequencing data.
Author: C. Titus Brown, Adam Taranto
Maintainer-email: "C. Titus Brown" <ctbrown@ucdavis.edu>
Requires-Python: >=3.10
